renderpy/__init__.py
renderpy/cli.py
renderpy/client.py
renderpy/deploy.py
renderpy/logs.py
renderpy/services.py
renderpy/utils.py
renderpy-1.0.0.dist-info/METADATA
renderpy-1.0.0.dist-info/WHEEL
renderpy-1.0.0.dist-info/entry_points.txt
renderpy-1.0.0.dist-info/top_level.txt
renderpy-1.0.0.dist-info/RECORD
