Metadata-Version: 2.4
Name: renderpy
Version: 1.0.0
Summary: Render CLI in Python
Home-page: https://github.com/ArsanCodifire/Render-PyCLI
Author: Arsan Codifire
Classifier: Programming Language :: Python :: 3
Classifier: Operating System :: OS Independent
Requires-Python: >=3.8
Requires-Dist: typer
Requires-Dist: httpx
Requires-Dist: rich
Requires-Dist: textual
Dynamic: author
Dynamic: classifier
Dynamic: description
Dynamic: description-content-type
Dynamic: home-page
Dynamic: requires-dist
Dynamic: requires-python
Dynamic: summary
